pyhorn/__init__.py
pyhorn/auth.py
pyhorn/client.py
pyhorn_flow-1.3.1.dist-info/LICENSE.txt
pyhorn_flow-1.3.1.dist-info/METADATA
pyhorn_flow-1.3.1.dist-info/WHEEL
pyhorn_flow-1.3.1.dist-info/top_level.txt
pyhorn_flow-1.3.1.dist-info/RECORD
