Metadata-Version: 2.1
Name: pyhorn-flow
Version: 1.3.1
Summary: An unofficial Bullhorn REST API client written in Python.
Home-page: https://github.com/flowef/pyhorn/
Author: Stephan Chang
Author-email: stephan.chang@flowef.com
License: UNKNOWN
Platform: UNKNOWN
Classifier: Programming Language :: Python :: 3
Classifier: License :: OSI Approved :: MIT License
Classifier: Operating System :: OS Independent
